mrp/__init__.py
mrp/life_cycle.py
mrp/process_def.py
mrp/util.py
mrp/cmd/__init__.py
mrp/cmd/_autocomplete.py
mrp/cmd/attach.py
mrp/cmd/down.py
mrp/cmd/info.py
mrp/cmd/logs.py
mrp/cmd/ps.py
mrp/cmd/up.py
mrp/cmd/wait.py
mrp/runtime/__init__.py
mrp/runtime/base.py
mrp/runtime/conda.py
mrp/runtime/docker.py
mrp/runtime/host.py
mrp/tool/__init__.py
mrp-1.0.4.dist-info/METADATA
mrp-1.0.4.dist-info/WHEEL
mrp-1.0.4.dist-info/entry_points.txt
mrp-1.0.4.dist-info/top_level.txt
mrp-1.0.4.dist-info/RECORD
