Metadata-Version: 2.1
Name: mrp
Version: 1.0.4
Summary: UNKNOWN
Home-page: UNKNOWN
Author: Leonid Shamis
License: UNKNOWN
Platform: UNKNOWN
Requires-Python: >=3.7
Requires-Dist: aiodocker (>=0.21.0)
Requires-Dist: alephzero (>=0.3.11)
Requires-Dist: click (>=8.0.3)
Requires-Dist: docker (>=5.0.0)
Requires-Dist: psutil (>=5.8.0)
Requires-Dist: pyyaml (>=6.0)
Requires-Dist: six (>=1.16.0)
